{
  "productos": [
    {
      "uego": "god",
      "precio": "40.000",
      "imagen": "https://images.pexels.com/photos/17612776/pexels-photo-17612776/free-photo-of-comida-resfriado-frio-sano.jpeg?auto=compress&cs=tinysrgb&w=600",
      "Categoria": "RPG",
      "breve": "adgawdgusghdjahuwdh",
      "amplio": "ajwudguawhdusgdugwudghawfwadwda",
      "Desarrollador": "Logan Paul",
      "id": 0
    },
    {
      "Juego": "ARK envolved",
      "precio": "1245",
      "imagen": "http://localhost:5173/administrador/FormularioProducto",
      "Genero": [
        "Simulación",
        "Terror"
      ],
      "breve": "awdawdawdawdawdawdawdawdawdawdaw",
      "amplio": "dadwadawawdawdawdawdawdawdawdawdawdawd",
      "Desarrollador": "adwdawd",
      "JuegoDeSemana": "true",
      "id": 1
    }
  ]
}